{"errors":[],"warnings":[],"namedChunkGroups":{"app":{"chunks":[9,3],"assets":["webpack-runtime-0a57a96a38e2d5dcc04c.js","webpack-runtime-0a57a96a38e2d5dcc04c.js.map","app-272c5ef9a837b56acbce.js","app-272c5ef9a837b56acbce.js.map"],"children":{},"childAssets":{}},"component---src-pages-404-js":{"chunks":[0,1,2,4],"assets":["styles.3a0cf75b37421c0f6db1.css","styles-7f42920828c2147843dd.js","styles-7f42920828c2147843dd.js.map","1-4ea351c3e9cca914cdd1.js","1-4ea351c3e9cca914cdd1.js.map","2-5fb8900adb97a6dd5ebc.js","2-5fb8900adb97a6dd5ebc.js.map","component---src-pages-404-js-036f58c4af52b2f490fd.js","component---src-pages-404-js-036f58c4af52b2f490fd.js.map"],"children":{},"childAssets":{}},"component---src-pages-index-js":{"chunks":[0,1,2,10,5],"assets":["styles.3a0cf75b37421c0f6db1.css","styles-7f42920828c2147843dd.js","styles-7f42920828c2147843dd.js.map","1-4ea351c3e9cca914cdd1.js","1-4ea351c3e9cca914cdd1.js.map","2-5fb8900adb97a6dd5ebc.js","2-5fb8900adb97a6dd5ebc.js.map","10-4daf280548511b2b715b.js","10-4daf280548511b2b715b.js.map","component---src-pages-index-js-a63cced6c39e1b798016.js","component---src-pages-index-js-a63cced6c39e1b798016.js.map"],"children":{},"childAssets":{}},"component---src-pages-packages-js":{"chunks":[0,1,6],"assets":["styles.3a0cf75b37421c0f6db1.css","styles-7f42920828c2147843dd.js","styles-7f42920828c2147843dd.js.map","1-4ea351c3e9cca914cdd1.js","1-4ea351c3e9cca914cdd1.js.map","component---src-pages-packages-js-e43d9935079afcfcc928.js","component---src-pages-packages-js-e43d9935079afcfcc928.js.map"],"children":{},"childAssets":{}},"component---src-pages-page-2-js":{"chunks":[0,1,2,7],"assets":["styles.3a0cf75b37421c0f6db1.css","styles-7f42920828c2147843dd.js","styles-7f42920828c2147843dd.js.map","1-4ea351c3e9cca914cdd1.js","1-4ea351c3e9cca914cdd1.js.map","2-5fb8900adb97a6dd5ebc.js","2-5fb8900adb97a6dd5ebc.js.map","component---src-pages-page-2-js-0f0cdaf5ef79c56177d5.js","component---src-pages-page-2-js-0f0cdaf5ef79c56177d5.js.map"],"children":{},"childAssets":{}},"pages-manifest":{"chunks":[8],"assets":["pages-manifest-7776806f0190d3d57891.js","pages-manifest-7776806f0190d3d57891.js.map"],"children":{},"childAssets":{}}},"assetsByChunkName":{"app":["webpack-runtime-0a57a96a38e2d5dcc04c.js","app-272c5ef9a837b56acbce.js"],"component---src-pages-404-js":["styles.3a0cf75b37421c0f6db1.css","styles-7f42920828c2147843dd.js","1-4ea351c3e9cca914cdd1.js","2-5fb8900adb97a6dd5ebc.js","component---src-pages-404-js-036f58c4af52b2f490fd.js"],"component---src-pages-index-js":["styles.3a0cf75b37421c0f6db1.css","styles-7f42920828c2147843dd.js","1-4ea351c3e9cca914cdd1.js","2-5fb8900adb97a6dd5ebc.js","10-4daf280548511b2b715b.js","component---src-pages-index-js-a63cced6c39e1b798016.js"],"component---src-pages-packages-js":["styles.3a0cf75b37421c0f6db1.css","styles-7f42920828c2147843dd.js","1-4ea351c3e9cca914cdd1.js","component---src-pages-packages-js-e43d9935079afcfcc928.js"],"component---src-pages-page-2-js":["styles.3a0cf75b37421c0f6db1.css","styles-7f42920828c2147843dd.js","1-4ea351c3e9cca914cdd1.js","2-5fb8900adb97a6dd5ebc.js","component---src-pages-page-2-js-0f0cdaf5ef79c56177d5.js"],"pages-manifest":["pages-manifest-7776806f0190d3d57891.js"]}}